[
    {
        "APK": "S0undTV_v1.4_RC1_standalone.apk",
        "ReleaseDate": "2022-02-13T18:30:00.000Z",
        "ReleaseType": 0,
        "VersionCode": 113,
        "VersionName": "v1.4_RC1",
        "hasChangeLog": false
    },
    {
        "APK": "beta_111.apk",
        "ReleaseDate": "2021-12-16T19:22:00.000Z",
        "ReleaseType": 1,
        "VersionCode": 111,
        "VersionName": "111",
        "hasChangeLog": false
    },
    {
        "APK": "",
        "ReleaseDate": "",
        "ReleaseType": 3,
        "VersionCode": 113,
        "VersionName": "v1.4_RC1",
        "hasChangeLog": true
    }
]